caption_flow/__init__.py
caption_flow/cli.py
caption_flow/models.py
caption_flow/monitor.py
caption_flow/orchestrator.py
caption_flow/viewer.py
caption_flow/processors/__init__.py
caption_flow/processors/base.py
caption_flow/processors/huggingface.py
caption_flow/processors/local_filesystem.py
caption_flow/processors/webdataset.py
caption_flow/storage/__init__.py
caption_flow/storage/exporter.py
caption_flow/storage/manager.py
caption_flow/utils/__init__.py
caption_flow/utils/auth.py
caption_flow/utils/caption_utils.py
caption_flow/utils/certificates.py
caption_flow/utils/checkpoint_tracker.py
caption_flow/utils/chunk_tracker.py
caption_flow/utils/image_processor.py
caption_flow/utils/json_utils.py
caption_flow/utils/prompt_template.py
caption_flow/utils/vllm_config.py
caption_flow/workers/base.py
caption_flow/workers/caption.py
caption_flow/workers/data.py
caption_flow-0.4.2.dist-info/licenses/LICENSE
caption_flow-0.4.2.dist-info/METADATA
caption_flow-0.4.2.dist-info/WHEEL
caption_flow-0.4.2.dist-info/entry_points.txt
caption_flow-0.4.2.dist-info/top_level.txt
caption_flow-0.4.2.dist-info/RECORD
