Metadata-Version: 2.4
Name: caption-flow
Version: 0.4.2
Summary: Self-contained distributed community captioning system
Author-email: bghira <bghira@users.github.com>
License: MIT
Keywords: captioning,distributed,vllm,dataset,community
Classifier: Development Status :: 4 - Beta
Classifier: Intended Audience :: Developers
Classifier: License :: OSI Approved :: MIT License
Classifier: Programming Language :: Python :: 3
Classifier: Programming Language :: Python :: 3.11
Classifier: Programming Language :: Python :: 3.12
Requires-Python: <3.13,>=3.11
License-File: LICENSE
Requires-Dist: websockets>=12.0
Requires-Dist: pyarrow>=14.0.0
Requires-Dist: click>=8.1.0
Requires-Dist: pydantic>=2.0.0
Requires-Dist: aiofiles>=23.0.0
Requires-Dist: rich>=13.0.0
Requires-Dist: cryptography>=41.0.0
Requires-Dist: pyyaml>=6.0
Requires-Dist: certbot>=2.0.0
Requires-Dist: numpy>=1.24.0
Requires-Dist: pillow>=10.0.0
Requires-Dist: vllm<0.11.0,>=0.10.0
Requires-Dist: webdataset<2.0.0,>=1.0.2
Requires-Dist: pandas<3.0.0,>=2.3.1
Requires-Dist: arrow<2.0.0,>=1.3.0
Requires-Dist: datasets<5.0.0,>=4.0.0
Requires-Dist: boto3<2.0.0,>=1.40.11
Requires-Dist: torchdata<0.12.0,>=0.11.0
Requires-Dist: textual<6.0.0,>=5.3.0
Requires-Dist: urwid<4.0.0,>=3.0.2
Requires-Dist: webshart<0.5.0,>=0.4.3
Requires-Dist: pylance<0.36.0,>=0.35.0
Requires-Dist: duckdb<2.0.0,>=1.3.2
Provides-Extra: dev
Requires-Dist: pytest>=7.4.0; extra == "dev"
Requires-Dist: pytest-asyncio>=0.21.0; extra == "dev"
Requires-Dist: pytest-cov>=4.1.0; extra == "dev"
Requires-Dist: black>=23.0.0; extra == "dev"
Requires-Dist: ruff>=0.1.0; extra == "dev"
Requires-Dist: mypy>=1.5.0; extra == "dev"
Dynamic: license-file
